zpp_store/__init__.py
zpp_store/input.py
zpp_store/store.py
zpp_store/structure.py
zpp_store-0.5.1.dist-info/licenses/LICENSE
zpp_store-0.5.1.dist-info/METADATA
zpp_store-0.5.1.dist-info/WHEEL
zpp_store-0.5.1.dist-info/top_level.txt
zpp_store-0.5.1.dist-info/RECORD
