Metadata-Version: 2.4
Name: zpp_store
Version: 0.5.1
Summary: SystÃ¨me de sÃ©rialisation de donnÃ©es
Home-page: https://github.com/ZephyrOff/zpp_store
Author: 
License: mit
Project-URL: Documentation, https://github.com/ZephyrOff/zpp_store
Keywords: store zephyroff
Platform: ALL
Classifier: Development Status :: 5 - Production/Stable
Classifier: Environment :: Console
Classifier: License :: OSI Approved :: MIT License
Classifier: Programming Language :: Python :: 3
License-File: LICENSE
Requires-Dist: PyYAML
Requires-Dist: msgpack
Requires-Dist: cryptography
Dynamic: classifier
Dynamic: description
Dynamic: description-content-type
Dynamic: home-page
Dynamic: keywords
Dynamic: license
Dynamic: license-file
Dynamic: platform
Dynamic: project-url
Dynamic: requires-dist
Dynamic: summary
